{
  "data":[
    {
      "name": "神经血液系统",
      "arr": [
        {
          "name": "神经痛",
          "value": "神经痛"
        },
        {
          "name": "血压异常",
          "value": "血压异常"
        },
        {
          "name": "血糖异常",
          "value": "血糖异常"
        },
        {
          "name": "补益调节",
          "value": "补益调节"
        },
        {
          "name": "睡眠障碍",
          "value": "睡眠障碍"
        },
        {
          "name": "体温异常",
          "value": "体温异常"
        },
        {
          "name": "高血脂",
          "value": "高血脂"
        },
        {
          "name": "其他",
          "value": "其他"
        },
        {
          "name": "精神疾病",
          "value": "精神疾病"
        }
      ]
    },
    {
      "name": "眼睛",
      "arr": [
        {
          "name": "屈光不正",
          "value": "屈光不正"
        },
        {
          "name": "红眼痛痒",
          "value": "红眼痛痒"
        },
        {
          "name": "麦粒肿",
          "value": "麦粒肿"
        },
        {
          "name": "飞蚊症",
          "value": "飞蚊症"
        }
      ]
    },
    {
      "name": "鼻子",
      "arr": [
        {
          "name": "鼻炎",
          "value": "鼻炎"
        },
        {
          "name": "鼻出血",
          "value": "鼻出血"
        }
      ]
    },
    {
      "name": "耳朵",
      "arr": [
        {
          "name": "耳鸣",
          "value": "耳鸣"
        },
        {
          "name": "耳聋",
          "value": "耳聋"
        },
        {
          "name":"中耳炎",
          "value":"中耳炎"
        }
      ]
    },
    {
      "name": "腹部",
      "arr": [
        {
          "name": "胃炎",
          "value": "胃炎"
        },
        {
          "name": "肠炎",
          "value": "肠炎"
        },
        {
          "name":"肝胆疾病",
          "value":"肝胆疾病"
        },
        {
          "name":"其他疾病",
          "value":"其他疾病"
        }
      ]
    },
    {
      "name": "生殖、肝部",
      "arr": [
        {
          "name": "肾炎",
          "value": "肾炎"
        },
        {
          "name": "泌尿系统",
          "value": "泌尿系统"
        },
        {
          "name":"男女生殖器官",
          "value":"男女生殖器官"
        },
        {
          "name":"痔疮",
          "value":"痔疮"
        },
        {
          "name":"脱肛、肛裂",
          "value":"脱肛、肛裂"
        }
      ]
    },
    {
      "name": "头部",
      "arr": [
        {
          "name": "头痛",
          "value": "头痛"
        },
        {
          "name": "头晕",
          "value": "头晕"
        },
        {
          "name":"脱发白发",
          "value":"脱发白发"
        },
        {
          "name":"脑部疾病",
          "value":"脑部疾病"
        }
      ]
    },
    {
      "name":"颈肩部",
      "arr":[
        {
          "name": "肩周炎",
          "value": "肩周炎"
        },
        {
          "name": "颈椎病",
          "value": "颈椎病"
        },
        {
          "name":"落枕",
          "value":"落枕"
        },
        {
          "name":"甲状腺",
          "value":"甲状腺"
        }
      ]
    },
    {
      "name":"口咽部",
      "arr":[
        {
          "name": "咽喉炎",
          "value": "咽喉炎"
        },
        {
          "name": "口舌溃疡",
          "value": "口舌溃疡"
        },
        {
          "name":"口臭",
          "value":"口臭"
        },
        {
          "name":"牙炎牙痛",
          "value":"牙炎牙痛"
        }
      ]
    },
    {
      "name":"胸部",
      "arr":[
        {
          "name": "支气管、肺炎",
          "value": "支气管、肺炎"
        },
        {
          "name": "乳房疾病",
          "value": "乳房疾病"
        },
        {
          "name":"心脏疾病",
          "value":"心脏疾病"
        },
        {
          "name":"肺结核",
          "value":"肺结核"
        }
      ]
    },
    {
      "name":"四肢",
      "arr":[
        {
          "name": "骨伤",
          "value": "骨伤"
        },
        {
          "name": "关节炎",
          "value": "关节炎"
        },
        {
          "name":"骨结核",
          "value":"骨结核"
        }
      ]
    },
    {
      "name":"皮肤",
      "arr":[
        {
          "name": "皮炎、湿疹、癣",
          "value": "皮炎、湿疹、癣"
        },
        {
          "name": "银屑病",
          "value": "银屑病"
        },
        {
          "name":"灰指甲",
          "value":"灰指甲"
        },
        {
          "name":"痤疮",
          "value":"痤疮"
        },
        {
          "name":"色斑疤痕",
          "value":"色斑疤痕"
        }
      ]
    }
  ]
}
